self_make/__init__.py
self_make-0.1.0.dist-info/WHEEL
self_make-0.1.0.dist-info/METADATA
self_make-0.1.0.dist-info/RECORD
